docs/Makefile
docs/conf.py
docs/index.rst
docs/make.bat
docs/requirements.txt
docs/exts/numfig.py
docs/pysiaf/aperture.rst
docs/pysiaf/compare.rst
docs/pysiaf/index.rst
docs/pysiaf/polynomial.rst
docs/pysiaf/projection.rst
docs/pysiaf/read.rst
docs/pysiaf/rotations.rst
docs/pysiaf/siaf.rst
docs/pysiaf/tools.rst
docs/pysiaf/write.rst
examples/check_detector_channels.ipynb
examples/extract_xml_field_formats.py
examples/make_nircam_siaf_figures.ipynb
examples/make_nircam_siaf_figures_script.py
examples/figures/HST_apertures.png
examples/figures/JWST_master_apertures.png
examples/figures/NIRISS_apertures.png
generate/__init__.py
generate/generate_fgs.py
generate/generate_miri.py
generate/generate_nircam.py
generate/generate_niriss.py
generate/generate_nirspec.py
generate/generate_reference_files.py
pysiaf/__init__.py
pysiaf/aperture.py
pysiaf/constants.py
pysiaf/siaf.py
pysiaf/specpars.py
pysiaf/version.py
pysiaf/iando/__init__.py
pysiaf/iando/read.py
pysiaf/iando/write.py
pysiaf/prd_data/HST/amu.rep-1.09
pysiaf/prd_data/HST/amu.rep-1.10
pysiaf/prd_data/HST/amu.rep-1.11
pysiaf/prd_data/HST/amu.rep-1.12
pysiaf/prd_data/HST/amu.rep-Latest
pysiaf/prd_data/HST/siaf.dat-1.83
pysiaf/prd_data/HST/siaf.dat-1.84
pysiaf/prd_data/HST/siaf.dat-1.85
pysiaf/prd_data/HST/siaf.dat-1.90
pysiaf/prd_data/HST/siaf.dat-Latest
pysiaf/prd_data/JWST/PRDOPSSOC-028/SIAFXML/Excel/FGS_SIAF.xlsx
pysiaf/prd_data/JWST/PRDOPSSOC-028/SIAFXML/Excel/MIRI_SIAF.xlsx
pysiaf/prd_data/JWST/PRDOPSSOC-028/SIAFXML/Excel/NIRCam_SIAF.xlsx
pysiaf/prd_data/JWST/PRDOPSSOC-028/SIAFXML/Excel/NIRISS_SIAF.xlsx
pysiaf/prd_data/JWST/PRDOPSSOC-028/SIAFXML/Excel/NIRSpec_SIAF.xlsx
pysiaf/prd_data/JWST/PRDOPSSOC-028/SIAFXML/SIAFXML/FGS_SIAF.xml
pysiaf/prd_data/JWST/PRDOPSSOC-028/SIAFXML/SIAFXML/MIRI_SIAF.xml
pysiaf/prd_data/JWST/PRDOPSSOC-028/SIAFXML/SIAFXML/NIRCam_SIAF.xml
pysiaf/prd_data/JWST/PRDOPSSOC-028/SIAFXML/SIAFXML/NIRISS_SIAF.xml
pysiaf/prd_data/JWST/PRDOPSSOC-028/SIAFXML/SIAFXML/NIRSpec_SIAF.xml
pysiaf-0.24.1.dist-info/LICENSE.md
pysiaf-0.24.1.dist-info/METADATA
pysiaf-0.24.1.dist-info/WHEEL
pysiaf-0.24.1.dist-info/top_level.txt
pysiaf-0.24.1.dist-info/RECORD
