Metadata-Version: 2.1
Name: pysiaf
Version: 0.24.1
Summary: Handling of Science Instrument Aperture Files (SIAF) for space telescopes
Author-email: STScI <help@stsci.edu>
License: BSD 3-Clause License
Project-URL: documentation, https://pysiaf.readthedocs.io/en/latest/
Project-URL: repository, https://github.com/spacetelescope/pysiaf
Classifier: Intended Audience :: Science/Research
Classifier: License :: OSI Approved :: BSD License
Classifier: Operating System :: OS Independent
Classifier: Programming Language :: Python
Classifier: Topic :: Scientific/Engineering :: Astronomy
Classifier: Topic :: Software Development :: Libraries :: Python Modules
Requires-Python: >=3.10
License-File: LICENSE.md
Requires-Dist: astropy>=4.3.1
Requires-Dist: lxml>=4.6.4
Requires-Dist: matplotlib>=3.4.3
Requires-Dist: numpy>=1.21.4
Requires-Dist: openpyxl>=3.0.9
Requires-Dist: requests>=2.26.0
Requires-Dist: scipy>=1.7.2
Provides-Extra: test
Requires-Dist: pytest; extra == "test"
Provides-Extra: docs
Requires-Dist: stsci-rtd-theme; extra == "docs"
Requires-Dist: sphinx-rtd-theme>=1.3.0; extra == "docs"
Requires-Dist: sphinx-automodapi; extra == "docs"
Requires-Dist: sphinx>=7.2.5; extra == "docs"
Requires-Dist: numpy; extra == "docs"
Requires-Dist: numpydoc>=1.1.0; extra == "docs"
Requires-Dist: matplotlib; extra == "docs"
Requires-Dist: scipy; extra == "docs"
Requires-Dist: tomli; python_version < "3.11" and extra == "docs"
